PyNeuralNetwork/EvolutionaryNeuralNetwork.py
PyNeuralNetwork/Globals.py
PyNeuralNetwork/MNIST.py
PyNeuralNetwork/NeuralNetwork.py
PyNeuralNetwork/Tests.py
PyNeuralNetwork/_CppInterface.py
PyNeuralNetwork/__init__.py
PyNeuralNetwork/ActivationFunctions/LeakyReLU.py
PyNeuralNetwork/ActivationFunctions/Linear.py
PyNeuralNetwork/ActivationFunctions/PlotActivationFunction.py
PyNeuralNetwork/ActivationFunctions/ReLU.py
PyNeuralNetwork/ActivationFunctions/Sigmoid.py
PyNeuralNetwork/ActivationFunctions/Softmax.py
PyNeuralNetwork/ActivationFunctions/Softplus.py
PyNeuralNetwork/ActivationFunctions/Tanh.py
PyNeuralNetwork/ActivationFunctions/__init__.py
PyNeuralNetwork/Autoencoder/Autoencoder.py
PyNeuralNetwork/Autoencoder/CrossEntropyCost.py
PyNeuralNetwork/Autoencoder/MeanSquareCost.py
PyNeuralNetwork/Autoencoder/ReLU.py
PyNeuralNetwork/Autoencoder/Sigmoid.py
PyNeuralNetwork/Autoencoder/__init__.py
PyNeuralNetwork/CostFunctions/CrossEntropyCost.py
PyNeuralNetwork/CostFunctions/MeanSquareCost.py
PyNeuralNetwork/CostFunctions/_Regularization.py
PyNeuralNetwork/CostFunctions/__init__.py
PyNeuralNetwork/PyNet/AnimateNeuralNetwork.py
PyNeuralNetwork/PyNet/NeuralNetwork.py
PyNeuralNetwork/PyNet/PlotNetwork.py
PyNeuralNetwork/PyNet/__init__.py
PyNeuralNetwork/Tools/BoxCox.py
PyNeuralNetwork/Tools/MultiProgressBar.py
PyNeuralNetwork/Tools/PlotCircle.py
PyNeuralNetwork/Tools/RemoveAxisLabels.py
PyNeuralNetwork/Tools/__init__.py
PyNeuralNetwork/__data/MNIST/0.bmp
PyNeuralNetwork/__data/MNIST/1.bmp
PyNeuralNetwork/__data/MNIST/2.bmp
PyNeuralNetwork/__data/MNIST/3.bmp
PyNeuralNetwork/__data/MNIST/4.bmp
PyNeuralNetwork/__data/MNIST/5.bmp
PyNeuralNetwork/__data/MNIST/6.bmp
PyNeuralNetwork/__data/MNIST/7.bmp
PyNeuralNetwork/__data/MNIST/8.bmp
PyNeuralNetwork/__data/MNIST/9.bmp
PyNeuralNetwork/__data/MNIST/t10k-images.idx3-ubyte
PyNeuralNetwork/__data/MNIST/t10k-labels.idx1-ubyte
PyNeuralNetwork/__data/MNIST/train-images.idx3-ubyte
PyNeuralNetwork/__data/MNIST/train-labels.idx1-ubyte
PyNeuralNetwork-0.0.1.dist-info/LICENSE
PyNeuralNetwork-0.0.1.dist-info/METADATA
PyNeuralNetwork-0.0.1.dist-info/WHEEL
PyNeuralNetwork-0.0.1.dist-info/top_level.txt
PyNeuralNetwork-0.0.1.dist-info/RECORD
